glebs_package/__init__.py
glebs_package/langident/__init__.py
glebs_package/langident/langident_pipeline.py
glebs_package/ocrqa/__init__.py
glebs_package/ocrqa/ocrqa_pipeline.py
glebs_package-1.3.0.dist-info/METADATA
glebs_package-1.3.0.dist-info/WHEEL
glebs_package-1.3.0.dist-info/top_level.txt
glebs_package-1.3.0.dist-info/RECORD
